log/__init__.py
met/__init__.py
pix/__init__.py
ucass/__init__.py
AeroSAM_logger-0.0.24.dist-info/LICENSE
AeroSAM_logger-0.0.24.dist-info/METADATA
AeroSAM_logger-0.0.24.dist-info/WHEEL
AeroSAM_logger-0.0.24.dist-info/top_level.txt
AeroSAM_logger-0.0.24.dist-info/RECORD
